.gitignore
.travis.yml
setup.py
tox.ini
csl_data/__init__.py
csl_data/_bridge.py
csl_data/_date_fragment.py
csl_data/_fragments.py
csl_data/csl-data.json
csl_data/document.py
csl_data/item.py
csl_data/schema.py
csl_data.egg-info/PKG-INFO
csl_data.egg-info/SOURCES.txt
csl_data.egg-info/dependency_links.txt
csl_data.egg-info/pbr.json
csl_data.egg-info/requires.txt
csl_data.egg-info/top_level.txt
tests/__init__.py
tests/test_date.py
tests/test_document.py
tests/test_item.py
tests/test_name.py
tests/test_schema.py
tests/utils.py