Metadata-Version: 1.1
Name: csl-data
Version: 0.1.1
Summary: CSL data structure.
Home-page: https://github.com/jayvdb/csl-data
Author: John Vandenberg
Author-email: jayvdb@gmail.com
License: MIT
Keywords: c,s,l, ,j,s,o,n, ,s,c,h,e,m,a, ,p,u,b,l,i,c,a,t,i,o,n, ,a,r,t,i,c,l,e, ,j,o,u,r,n,a,l
Platform: UNKNOWN
Classifier: Development Status :: 3 - Alpha
Classifier: Environment :: Console
Classifier: Intended Audience :: Developers
Classifier: License :: OSI Approved :: MIT License
Classifier: Operating System :: OS Independent
Classifier: Programming Language :: Python
Classifier: Programming Language :: Python :: 2
Classifier: Programming Language :: Python :: 3
Classifier: Programming Language :: Python :: Implementation :: CPython
Classifier: Programming Language :: Python :: Implementation :: PyPy
Classifier: Topic :: Software Development :: Libraries :: Python Modules
Classifier: Topic :: Software Development :: Build Tools
